happysim-0.1.3.dist-info/licenses/LICENSE
happysimulator/__init__.py
happysimulator/py.typed
happysimulator/components/__init__.py
happysimulator/components/leaky_bucket_rate_limiter.py
happysimulator/components/queue.py
happysimulator/components/queue_driver.py
happysimulator/components/queue_policy.py
happysimulator/components/queued_resource.py
happysimulator/components/random_router.py
happysimulator/components/sliding_window_rate_limiter.py
happysimulator/components/token_bucket_rate_limiter.py
happysimulator/components/client/__init__.py
happysimulator/components/client/client.py
happysimulator/components/client/connection_pool.py
happysimulator/components/client/pooled_client.py
happysimulator/components/client/retry.py
happysimulator/components/datastore/__init__.py
happysimulator/components/datastore/cache_warming.py
happysimulator/components/datastore/cached_store.py
happysimulator/components/datastore/database.py
happysimulator/components/datastore/eviction_policies.py
happysimulator/components/datastore/kv_store.py
happysimulator/components/datastore/multi_tier_cache.py
happysimulator/components/datastore/replicated_store.py
happysimulator/components/datastore/sharded_store.py
happysimulator/components/datastore/write_policies.py
happysimulator/components/load_balancer/__init__.py
happysimulator/components/load_balancer/health_check.py
happysimulator/components/load_balancer/load_balancer.py
happysimulator/components/load_balancer/strategies.py
happysimulator/components/messaging/__init__.py
happysimulator/components/messaging/dlq.py
happysimulator/components/messaging/message_queue.py
happysimulator/components/messaging/topic.py
happysimulator/components/network/__init__.py
happysimulator/components/network/conditions.py
happysimulator/components/network/link.py
happysimulator/components/network/network.py
happysimulator/components/queue_policies/__init__.py
happysimulator/components/queue_policies/adaptive_lifo.py
happysimulator/components/queue_policies/codel.py
happysim-0.1.3.dist-info/METADATA
happysim-0.1.3.dist-info/WHEEL
happysim-0.1.3.dist-info/top_level.txt
happysim-0.1.3.dist-info/RECORD
