Metadata-Version: 2.4
Name: happysim
Version: 0.1.3
Summary: Discrete event simulation library for Python, similar to MATLAB SimEvent
Author: adamfilli
License-Expression: Apache-2.0
Project-URL: Homepage, https://github.com/adamfilli/happy-simulator
Project-URL: Repository, https://github.com/adamfilli/happy-simulator
Project-URL: Issues, https://github.com/adamfilli/happy-simulator/issues
Keywords: simulation,discrete-event,event-driven,modeling,simevents
Classifier: Development Status :: 3 - Alpha
Classifier: Intended Audience :: Developers
Classifier: Intended Audience :: Science/Research
Classifier: Operating System :: OS Independent
Classifier: Programming Language :: Python :: 3
Classifier: Programming Language :: Python :: 3.13
Classifier: Topic :: Scientific/Engineering
Classifier: Typing :: Typed
Requires-Python: >=3.13
License-File: LICENSE
Requires-Dist: matplotlib
Requires-Dist: numpy
Requires-Dist: pandas
Requires-Dist: scipy
Provides-Extra: dev
Requires-Dist: pytest>=7.0; extra == "dev"
Requires-Dist: pytest-cov; extra == "dev"
Requires-Dist: mypy; extra == "dev"
Requires-Dist: ruff; extra == "dev"
Requires-Dist: mkdocs-material; extra == "dev"
Dynamic: license-file
